alibabacloud_aiccs20230516/__init__.py
alibabacloud_aiccs20230516/client.py
alibabacloud_aiccs20230516/models/__init__.py
alibabacloud_aiccs20230516/models/_add_agent_group_request.py
alibabacloud_aiccs20230516/models/_add_agent_group_response.py
alibabacloud_aiccs20230516/models/_add_agent_group_response_body.py
alibabacloud_aiccs20230516/models/_add_agent_request.py
alibabacloud_aiccs20230516/models/_add_agent_response.py
alibabacloud_aiccs20230516/models/_add_agent_response_body.py
alibabacloud_aiccs20230516/models/_add_blacklist_request.py
alibabacloud_aiccs20230516/models/_add_blacklist_response.py
alibabacloud_aiccs20230516/models/_add_blacklist_response_body.py
alibabacloud_aiccs20230516/models/_add_blacklist_shrink_request.py
alibabacloud_aiccs20230516/models/_add_task_request.py
alibabacloud_aiccs20230516/models/_add_task_response.py
alibabacloud_aiccs20230516/models/_add_task_response_body.py
alibabacloud_aiccs20230516/models/_add_task_shrink_request.py
alibabacloud_aiccs20230516/models/_agent_call_list_request.py
alibabacloud_aiccs20230516/models/_agent_call_list_response.py
alibabacloud_aiccs20230516/models/_agent_call_list_response_body.py
alibabacloud_aiccs20230516/models/_agent_call_list_shrink_request.py
alibabacloud_aiccs20230516/models/_agent_cancel_call_request.py
alibabacloud_aiccs20230516/models/_agent_cancel_call_response.py
alibabacloud_aiccs20230516/models/_agent_cancel_call_response_body.py
alibabacloud_aiccs20230516/models/_agent_cancel_call_shrink_request.py
alibabacloud_aiccs20230516/models/_agent_group_page_request.py
alibabacloud_aiccs20230516/models/_agent_group_page_response.py
alibabacloud_aiccs20230516/models/_agent_group_page_response_body.py
alibabacloud_aiccs20230516/models/_agent_import_number_request.py
alibabacloud_aiccs20230516/models/_agent_import_number_response.py
alibabacloud_aiccs20230516/models/_agent_import_number_response_body.py
alibabacloud_aiccs20230516/models/_agent_import_number_shrink_request.py
alibabacloud_aiccs20230516-1.2.1.dist-info/LICENSE
alibabacloud_aiccs20230516-1.2.1.dist-info/METADATA
alibabacloud_aiccs20230516-1.2.1.dist-info/WHEEL
alibabacloud_aiccs20230516-1.2.1.dist-info/top_level.txt
alibabacloud_aiccs20230516-1.2.1.dist-info/RECORD
